MANIFEST.in
README.rst
requirements.txt
setup.py
sshjob/__init__.py
sshjob/job_queues.py
sshjob/multisys.py
sshjob/shell_runs.py
sshjob/sshjob.py
sshjob/track.py
sshjob.egg-info/PKG-INFO
sshjob.egg-info/SOURCES.txt
sshjob.egg-info/dependency_links.txt
sshjob.egg-info/entry_points.txt
sshjob.egg-info/top_level.txt