Metadata-Version: 1.2
Name: sshjob
Version: 0.0.dev26
Summary: Submit HPC jobs via ssh from Python
Home-page: https://github.com/shuheikurita/sshjob
Author: shuheikurita
Author-email: shuheikurita@example.jp
Maintainer: shuheikurita
Maintainer-email: shuheikurita@example.jp
License: GPLv2
Platform: UNKNOWN
Classifier: Programming Language :: Python :: 2
Classifier: Programming Language :: Python :: 2.7
Classifier: Programming Language :: Python :: 3
Classifier: Programming Language :: Python :: 3.4
Classifier: Programming Language :: Python :: 3.5
Classifier: Programming Language :: Python :: 3.6
Classifier: Programming Language :: Python :: 3.7
Classifier: License :: OSI Approved :: GNU General Public License v2 (GPLv2)
